benchmarks/__init__.py
benchmarks/tabular_bench.py
benchmarks/vision_bench.py
deepchecks/__init__.py
deepchecks/checks.py
deepchecks/ppscore.py
deepchecks/suites.py
deepchecks/analytics/__init__.py
deepchecks/analytics/anonymous_telemetry.py
deepchecks/core/__init__.py
deepchecks/core/check_json.py
deepchecks/core/check_result.py
deepchecks/core/checks.py
deepchecks/core/common.py
deepchecks/core/condition.py
deepchecks/core/context.py
deepchecks/core/display.py
deepchecks/core/errors.py
deepchecks/core/reduce_classes.py
deepchecks/core/suite.py
deepchecks/core/check_utils/__init__.py
deepchecks/core/check_utils/class_performance_utils.py
deepchecks/core/check_utils/feature_label_correlation_utils.py
deepchecks/core/check_utils/multivariate_drift_utils.py
deepchecks/core/check_utils/single_dataset_performance_base.py
deepchecks/core/resources/__init__.py
deepchecks/core/resources/jupyterlab-plotly.js
deepchecks/core/resources/requirejs.min.js
deepchecks/core/resources/suite-template-full.html
deepchecks/core/resources/suite-template.html
deepchecks/core/resources/widgets-embed-amd.js
deepchecks/core/resources/widgets-embed.js
deepchecks/core/serialization/__init__.py
deepchecks/core/serialization/abc.py
deepchecks/core/serialization/common.py
deepchecks/core/serialization/html_display.py
deepchecks/core/serialization/check_failure/__init__.py
deepchecks/core/serialization/check_failure/html.py
deepchecks/core/serialization/check_failure/ipython.py
deepchecks/core/serialization/check_failure/json.py
deepchecks/core/serialization/check_failure/junit.py
deepchecks/core/serialization/check_failure/wandb.py
deepchecks/core/serialization/check_failure/widget.py
deepchecks/core/serialization/check_result/__init__.py
deepchecks/core/serialization/check_result/html.py
deepchecks/core/serialization/check_result/ipython.py
deepchecks/core/serialization/check_result/json.py
deepchecks/core/serialization/check_result/junit.py
deepchecks/core/serialization/check_result/wandb.py
deepchecks-0.19.1.dist-info/LICENSE
deepchecks-0.19.1.dist-info/METADATA
deepchecks-0.19.1.dist-info/WHEEL
deepchecks-0.19.1.dist-info/top_level.txt
deepchecks-0.19.1.dist-info/RECORD
