Metadata-Version: 2.1
Name: deepchecks
Version: 0.19.1
Summary: Package for validating your machine learning model and data
Home-page: https://github.com/deepchecks/deepchecks
Author: deepchecks
Author-email: info@deepchecks.com
License: UNKNOWN
Download-URL: https://github.com/deepchecks/deepchecks/releases/download/0.19.1/deepchecks-0.19.1.tar.gz
Project-URL: Documentation, https://docs.deepchecks.com
Project-URL: Bug Reports, https://github.com/deepchecks/deepchecks
Project-URL: Source, https://github.com/deepchecks/deepchecks
Project-URL: Contribute!, https://github.com/deepchecks/deepchecks/blob/master/CONTRIBUTING.md
Keywords: Software Development,Machine Learning
Platform: UNKNOWN
Classifier: Intended Audience :: Developers
Classifier: Intended Audience :: Science/Research
Classifier: Topic :: Software Development
Classifier: Topic :: Scientific/Engineering
Classifier: License :: OSI Approved :: GNU Affero General Public License v3 or later (AGPLv3+)
Classifier: Programming Language :: Python :: 3
Classifier: Programming Language :: Python :: 3.6
Classifier: Programming Language :: Python :: 3.7
Classifier: Programming Language :: Python :: 3.8
Classifier: Programming Language :: Python :: 3.9
Classifier: Programming Language :: Python :: 3.10
Provides-Extra: vision
Provides-Extra: nlp
Provides-Extra: nlp-properties
License-File: LICENSE
